sample_dataset/__init__.py
sample_dataset/cli.py
sample_dataset/core.py
sample_dataset-0.3.0.dist-info/METADATA
sample_dataset-0.3.0.dist-info/WHEEL
sample_dataset-0.3.0.dist-info/licenses/LICENSE
sample_dataset-0.3.0.dist-info/RECORD
