Metadata-Version: 2.4
Name: sample-dataset
Version: 0.3.0
Summary: A library to create random balanced samples through constraint optimization
Project-URL: Homepage, https://github.com/LaboratorioSperimentale/sample-dataset
Project-URL: BugTracker, https://github.com/LaboratorioSperimentale/sample-dataset/issues
Author-email: Ludovica Pannitto <ellepannitto@gmail.com>
License:                     GNU GENERAL PUBLIC LICENSE
License-File: LICENSE
Classifier: License :: OSI Approved :: MIT License
Classifier: Operating System :: OS Independent
Classifier: Programming Language :: Python :: 3 :: Only
Classifier: Topic :: Scientific/Engineering
Requires-Python: >=3.9
Requires-Dist: numpy
Requires-Dist: ortools
Requires-Dist: pandas
Requires-Dist: setuptools
